assetlab/__init__.py
assetlab/bond.py
assetlab/cashflow.py
assetlab/deposit.py
assetlab/settings.py
assetlab-0.1.0.dist-info/licenses/LICENSE
assetlab-0.1.0.dist-info/METADATA
assetlab-0.1.0.dist-info/WHEEL
assetlab-0.1.0.dist-info/top_level.txt
assetlab-0.1.0.dist-info/RECORD
