Metadata-Version: 2.4
Name: assetlab
Version: 0.1.0
Summary: A powerful Python library for financial calculations, including cash flow analysis, asset valuation, and portfolio metrics.
Author-email: Maxim <MaximVUstinov@gmail.com>
License-Expression: MIT
Project-URL: Homepage, https://github.com/your-username/AssetLab
Project-URL: Repository, https://github.com/your-username/AssetLab
Classifier: Development Status :: 3 - Alpha
Classifier: Intended Audience :: Developers
Classifier: Intended Audience :: Financial and Insurance Industry
Classifier: Operating System :: OS Independent
Classifier: Programming Language :: Python :: 3
Classifier: Programming Language :: Python :: 3.9
Classifier: Programming Language :: Python :: 3.10
Classifier: Programming Language :: Python :: 3.11
Classifier: Programming Language :: Python :: 3.12
Classifier: Topic :: Office/Business :: Financial :: Investment
Classifier: Topic :: Software Development :: Libraries :: Python Modules
Requires-Python: >=3.9
License-File: LICENSE
Requires-Dist: pandas>=1.5.0
Requires-Dist: numpy>=1.23.0
Requires-Dist: pydantic>=2.0.0
Requires-Dist: scipy>=1.9.0
Requires-Dist: matplotlib>=3.7.0
Requires-Dist: notebook>=7.4.4
Provides-Extra: test
Requires-Dist: pytest>=7.0.0; extra == "test"
Provides-Extra: dev
Requires-Dist: assetlab[test]; extra == "dev"
Requires-Dist: tox>=4.0.0; extra == "dev"
Requires-Dist: coverage[toml]>=7.0.0; extra == "dev"
Requires-Dist: sphinx>=7.0.0; extra == "dev"
Requires-Dist: sphinx-rtd-theme>=1.3.0; extra == "dev"
Requires-Dist: sphinx-autodoc-typehints>=1.24.0; extra == "dev"
Requires-Dist: myst-parser>=2.0.0; extra == "dev"
Dynamic: license-file
